icon_image
